esperclient/__init__.py
esperclient/api_client.py
esperclient/configuration.py
esperclient/rest.py
esperclient/api/__init__.py
esperclient/api/application_api.py
esperclient/api/commands_api.py
esperclient/api/commands_v2_api.py
esperclient/api/content_api.py
esperclient/api/device_api.py
esperclient/api/device_group_api.py
esperclient/api/enterprise_api.py
esperclient/api/enterprise_policy_api.py
esperclient/api/geofence_api.py
esperclient/api/group_commands_api.py
esperclient/api/subscription_api.py
esperclient/api/token_api.py
esperclient/models/__init__.py
esperclient/models/app_install.py
esperclient/models/app_install_application.py
esperclient/models/app_install_state_enum.py
esperclient/models/app_install_version.py
esperclient/models/app_permission.py
esperclient/models/app_version.py
esperclient/models/application.py
esperclient/models/application_version.py
esperclient/models/command_args.py
esperclient/models/command_request.py
esperclient/models/content.py
esperclient/models/data.py
esperclient/models/device.py
esperclient/models/device_app.py
esperclient/models/device_app_permission.py
esperclient/models/device_command.py
esperclient/models/device_command_enum.py
esperclient/models/device_group.py
esperclient/models/device_group_partial_update.py
esperclient/models/device_group_update.py
esperclient/models/device_status.py
esperclient/models/emm_device.py
esperclient/models/emm_enterprise_state_enum.py
esperclient/models/enterprise.py
esperclient/models/enterprise_detail.py
esperclient/models/enterprise_policy.py
esperclient/models/enterprise_policy_data.py
esperclient/models/enterprise_policy_data_device_password_policy.py
esperclient/models/enterprise_policy_data_device_update_policy.py
esperclient/models/enterprise_policy_data_frp_googles.py
esperclient/models/enterprise_policy_data_google_account_permission.py
esperclient/models/enterprise_policy_data_phone_policy.py
esperclient/models/enterprise_policy_partial_update.py
esperclient-0.1.2.dist-info/METADATA
esperclient-0.1.2.dist-info/WHEEL
esperclient-0.1.2.dist-info/top_level.txt
esperclient-0.1.2.dist-info/RECORD
