Metadata-Version: 2.1
Name: esperclient
Version: 0.1.2
Summary: ESPER API REFERENCE
Home-page: UNKNOWN
Author-email: developer@esper.io
License: UNKNOWN
Keywords: Python SDK,ESPER API REFERENCE
Platform: UNKNOWN
Requires-Dist: certifi (>=2017.4.17)
Requires-Dist: python-dateutil (>=2.1)
Requires-Dist: six (>=1.10)
Requires-Dist: urllib3 (>=1.23)
